aiomc
