Metadata-Version: 2.1
Name: aiomc
Version: 0.0.4
Summary: Async Python wrapper for Minio Admin
Home-page: https://github.com/trisongz/aiomc
Author: Tri Songz
Author-email: ts@growthengineai.com
License: MIT Style
Platform: UNKNOWN
Classifier: Intended Audience :: Developers
Classifier: License :: OSI Approved :: MIT License
Classifier: Programming Language :: Python :: 3.7
Classifier: Topic :: Software Development :: Libraries
License-File: LICENSE.txt
